odoo/addons/stock_picking_restrict_cancel_with_orig_move/README.rst
odoo/addons/stock_picking_restrict_cancel_with_orig_move/__init__.py
odoo/addons/stock_picking_restrict_cancel_with_orig_move/__manifest__.py
odoo/addons/stock_picking_restrict_cancel_with_orig_move/i18n/it.po
odoo/addons/stock_picking_restrict_cancel_with_orig_move/i18n/stock_picking_restrict_cancel_with_orig_move.pot
odoo/addons/stock_picking_restrict_cancel_with_orig_move/models/__init__.py
odoo/addons/stock_picking_restrict_cancel_with_orig_move/models/stock_move.py
odoo/addons/stock_picking_restrict_cancel_with_orig_move/readme/CONTRIBUTORS.rst
odoo/addons/stock_picking_restrict_cancel_with_orig_move/readme/CREDITS.rst
odoo/addons/stock_picking_restrict_cancel_with_orig_move/readme/DESCRIPTION.rst
odoo/addons/stock_picking_restrict_cancel_with_orig_move/readme/USAGE.rst
odoo/addons/stock_picking_restrict_cancel_with_orig_move/static/description/icon.png
odoo/addons/stock_picking_restrict_cancel_with_orig_move/static/description/index.html
odoo/addons/stock_picking_restrict_cancel_with_orig_move/tests/__init__.py
odoo/addons/stock_picking_restrict_cancel_with_orig_move/tests/test_restrict_cancel.py
odoo14_addon_stock_picking_restrict_cancel_with_orig_move-14.0.1.0.2.dev5.dist-info/METADATA
odoo14_addon_stock_picking_restrict_cancel_with_orig_move-14.0.1.0.2.dev5.dist-info/WHEEL
odoo14_addon_stock_picking_restrict_cancel_with_orig_move-14.0.1.0.2.dev5.dist-info/top_level.txt
odoo14_addon_stock_picking_restrict_cancel_with_orig_move-14.0.1.0.2.dev5.dist-info/RECORD
